pipeline.v
module pipe_MIPS32(clk1,clk2);
input clk1, clk2;
reg [31:0] PC, IF_ID_IR, IF_ID_NPC;
reg [31:0] ID_EX_IR, ID_EX_NPC, ID_EX_A, ID_EX_B, ID_EX_Imm;
reg [31:0] EX_MEM_IR, EX_MEM_ALUOut, EX_MEM_B, EX_MEM_cond;
reg [31:0] MEM_WB_IR, MEM_WB_ALUOut, MEM_WB_LMD;
reg [2:0] ID_EX_type, EX_MEM_type, MEM_WB_type;

reg [31:0] register [0:31];
reg [31:0] memory [0:1023];
parameter ADD = 6'b000000, SUB = 6'b000001, AND = 6'b000010, OR = 6'b000011, SLT=6'b000100,
           MUL = 6'b000101, SW = 6'b000110, ORI = 6'b000111, SLTI = 6'b001000,
           LW = 6'b001001, ADDI = 6'b001010, BEQ = 6'b001011, BNE = 6'b001100,
           JUMP = 6'b001101, HLT=6'b111111;
parameter RR_ALU=3'b000, RM_Alu=3'b001, LOAD=3'b010, STORE=3'b011, BRANCH=3'b100, HALT=3'b101; 
reg HALTED;
reg TAKEN_BRANCH;
initial begin
    HALTED=0;
    TAKEN_BRANCH=0; 
    PC = 0; 
end
always @(posedge clk1) begin
    if(HALTED==0) begin
        if(((EX_MEM_IR[31:26] == BEQ) && (EX_MEM_cond == 1))||
           ((EX_MEM_IR[31:26] == BNE) && (EX_MEM_cond == 0))) begin
            IF_ID_IR <= #2 memory[EX_MEM_ALUOut];
            TAKEN_BRANCH <= #2 1'b1;
            IF_ID_NPC <= #2 EX_MEM_ALUOut + 1;
            PC<= #2 EX_MEM_ALUOut + 1;
        end else begin
            IF_ID_IR<= #2 memory[PC];
            IF_ID_NPC <= #2 PC + 1;
            PC <= PC + 1;
        end
    end
    
end
always @(posedge clk2) begin
    if(HALTED==0) begin
        if (IF_ID_IR[25:21]==5'b00000) ID_EX_A<=0; 
        else ID_EX_A <= #2 register[IF_ID_IR[25:21]];
        if (IF_ID_IR[20:16]==5'b00000) ID_EX_B<=0; 
        else ID_EX_B <= #2 register[IF_ID_IR[20:16]];
        ID_EX_IR <= #2 IF_ID_IR;
        ID_EX_NPC <= #2 IF_ID_NPC;
        ID_EX_Imm <= #2 {{16{IF_ID_IR[15]}}, IF_ID_IR[15:0]};
        case (IF_ID_IR[31:26])      
            ADD, SUB, AND, OR, SLT, MUL: ID_EX_type <= #2 RR_ALU;
            ADDI, ORI, SLTI: ID_EX_type <= #2 RM_Alu;
            LW: ID_EX_type <= #2 LOAD;
            SW: ID_EX_type <= #2 STORE;
            BEQ, BNE: ID_EX_type <= #2 BRANCH;
            HLT: ID_EX_type <= #2 HALT;
        endcase
    end
    
end
always @(posedge clk1) begin
    if (HALTED==0) begin
        EX_MEM_type<=#2 ID_EX_type;
        EX_MEM_IR <= #2 ID_EX_IR;
        TAKEN_BRANCH <= #2 1'b0;
        case (ID_EX_type)
            RR_ALU: begin
                case (ID_EX_IR[31:26])
                    ADD: EX_MEM_ALUOut <= #2 ID_EX_A + ID_EX_B;
                    SUB: EX_MEM_ALUOut <= #2 ID_EX_A - ID_EX_B;
                    AND: EX_MEM_ALUOut <= #2 ID_EX_A & ID_EX_B;
                    OR: EX_MEM_ALUOut <= #2 ID_EX_A | ID_EX_B;
                    SLT: EX_MEM_ALUOut <= #2 (ID_EX_A < ID_EX_B) ? 1 : 0;
                    MUL: EX_MEM_ALUOut <= #2 ID_EX_A * ID_EX_B;
                endcase
                
            end
            
            RM_Alu: begin
                $display("IMM Execute: Instruction = %h |A = %0d | Immediate = %0d (0x%h)", ID_EX_IR,ID_EX_A, ID_EX_Imm, ID_EX_Imm);
                case (ID_EX_IR[31:26])
                    ADDI: EX_MEM_ALUOut <= #2 ID_EX_A + ID_EX_Imm;
                    ORI:  EX_MEM_ALUOut <= #2 ID_EX_A | ID_EX_Imm;
                    SLTI: EX_MEM_ALUOut <= #2 (ID_EX_A < ID_EX_Imm) ? 1 : 0;
                    default: EX_MEM_ALUOut <= #2 32'hxxxxxxxx;
                endcase
            end

            
            LOAD: begin
                EX_MEM_ALUOut <= #2 ID_EX_A + ID_EX_Imm;
                EX_MEM_B <= #2 ID_EX_B; 
            end
            
            STORE: begin
                EX_MEM_ALUOut <= #2 ID_EX_A + ID_EX_Imm; 
                EX_MEM_B <= #2 ID_EX_B;
            end
            
            BRANCH: begin
                EX_MEM_ALUOut <= #2 ID_EX_NPC + ID_EX_Imm; 
                if (ID_EX_IR[31:26] == BEQ) begin
                    EX_MEM_cond <= #2 (ID_EX_A == ID_EX_B); 
                end else if (ID_EX_IR[31:26] == BNE) begin
                    EX_MEM_cond <= #2 (ID_EX_A != ID_EX_B); 
                end else begin
                    EX_MEM_cond <= #2 1'b0; 
                end
            end
        endcase      
    end
    
end
always @(posedge clk2) begin
    if (HALTED==0) begin
        MEM_WB_type<= #2EX_MEM_type;
        MEM_WB_IR <= #2 EX_MEM_IR;
        case (EX_MEM_type)
            RR_ALU, RM_Alu: begin
                MEM_WB_ALUOut <= #2 EX_MEM_ALUOut;
                MEM_WB_LMD <= #2 32'hxxxxxxxx; 
            end
            
            LOAD: begin
                MEM_WB_ALUOut <= #2 EX_MEM_ALUOut; 
                MEM_WB_LMD <= #2 memory[EX_MEM_ALUOut]; 
            end
            
            STORE: if (TAKEN_BRANCH ==0) begin
                memory[EX_MEM_ALUOut] <= #2 EX_MEM_B; 
                
            end
        endcase    
    end
    
end
always @(posedge clk1) begin
    if (TAKEN_BRANCH==0) begin
        
        case (MEM_WB_type)      
            RR_ALU: begin
                register[MEM_WB_IR[15:11]] <= #2 MEM_WB_ALUOut;
            
            end

            RM_Alu: begin
                register[MEM_WB_IR[20:16]] <= #2 MEM_WB_ALUOut;
            end

            LOAD: begin
                register[MEM_WB_IR[20:16]] <= #2 MEM_WB_LMD;
            end

            HALT: begin
                HALTED <= #2 1'b1; 
            end
        endcase
    end
    
end
    
endmodule

pipelinetxt.v
`include "pipeline.v"


module testpipeline;
    reg clk1, clk2;
    integer k;

    pipe_MIPS32 uut(
        .clk1(clk1),
        .clk2(clk2)
    );

    
    initial begin
        clk1 = 0; clk2 = 0;
        repeat(200) begin
            #5 clk1 = ~clk1;
            #5 clk2 = ~clk2;
        end
    end

   
    initial begin
       
        for (k = 0; k < 6; k = k + 1)
            uut.register[k] = k;

        uut.memory[0]  = 32'h2801000a; 
        uut.memory[1]  = 32'h28010014; 
        uut.memory[2]  = 32'h28010019; 
        uut.memory[3]  = 32'h0ce77800; 
        uut.memory[4]  = 32'h0ce77800; 
        uut.memory[5]  = 32'h00222000; 
        uut.memory[6]  = 32'h0ce77800; 
        uut.memory[7]  = 32'h00832800; 
        uut.memory[12] = 32'hfc000000; 
        #1500;
        for (k = 0; k < 6; k = k + 1)
            $display("Register %2d: %2d,", k, uut.register[k]);
    end
    initial begin
        $dumpfile("pipelinetxt.vcd");
        $dumpvars(0, uut);
        #1600;
        $finish;
    end

endmodule

pipelinetxt.vcd
$date
	Sun Jun 29 00:33:46 2025
$end
$version
	Icarus Verilog
$end
$timescale
	1s
$end
$scope module testpipeline $end
$scope module uut $end
$var wire 1 ! clk1 $end
$var wire 1 " clk2 $end
$var reg 32 # EX_MEM_ALUOut [31:0] $end
$var reg 32 $ EX_MEM_B [31:0] $end
$var reg 32 % EX_MEM_IR [31:0] $end
$var reg 32 & EX_MEM_cond [31:0] $end
$var reg 3 ' EX_MEM_type [2:0] $end
$var reg 1 ( HALTED $end
$var reg 32 ) ID_EX_A [31:0] $end
$var reg 32 * ID_EX_B [31:0] $end
$var reg 32 + ID_EX_IR [31:0] $end
$var reg 32 , ID_EX_Imm [31:0] $end
$var reg 32 - ID_EX_NPC [31:0] $end
$var reg 3 . ID_EX_type [2:0] $end
$var reg 32 / IF_ID_IR [31:0] $end
$var reg 32 0 IF_ID_NPC [31:0] $end
$var reg 32 1 MEM_WB_ALUOut [31:0] $end
$var reg 32 2 MEM_WB_IR [31:0] $end
$var reg 32 3 MEM_WB_LMD [31:0] $end
$var reg 3 4 MEM_WB_type [2:0] $end
$var reg 32 5 PC [31:0] $end
$var reg 1 6 TAKEN_BRANCH $end
$upscope $end
$upscope $end
$enddefinitions $end
#0
$dumpvars
06
b0 5
bx 4
bx 3
bx 2
bx 1
bx 0
bx /
bx .
bx -
bx ,
bx +
bx *
bx )
0(
bx '
bx &
bx %
bx $
bx #
0"
0!
$end
#5
b1 5
1!
#7
b1 0
b101000000000010000000000001010 /
#10
b0 )
1"
#12
b1 .
b1010 ,
b1 -
b101000000000010000000000001010 +
b1 *
#15
0!
#20
0"
#25
b10 5
1!
#27
b1010 #
b101000000000010000000000001010 %
b1 '
b10 0
b101000000000010000000000010100 /
#30
1"
#32
b1010 1
b101000000000010000000000001010 2
b1 4
b10100 ,
b10 -
b101000000000010000000000010100 +
#35
0!
#40
0"
#45
b11 5
1!
#47
b11 0
b101000000000010000000000011001 /
b10100 #
b101000000000010000000000010100 %
#50
1"
#52
b11001 ,
b11 -
b101000000000010000000000011001 +
b1010 *
b10100 1
b101000000000010000000000010100 2
#55
0!
#60
0"
#65
b100 5
1!
#67
b11001 #
b101000000000010000000000011001 %
b100 0
b1100111001110111100000000000 /
#70
1"
#72
b11001 1
b101000000000010000000000011001 2
b0 .
b111100000000000 ,
b100 -
b1100111001110111100000000000 +
bx *
bx )
#75
0!
#80
0"
#85
b101 5
1!
#87
b101 0
bx #
b1100111001110111100000000000 %
b0 '
#90
1"
#92
b101 -
bx 1
b1100111001110111100000000000 2
b0 4
#95
0!
#100
0"
#105
b110 5
1!
#107
b110 0
b1000100010000000000000 /
#110
1"
#112
b10000000000000 ,
b110 -
b1000100010000000000000 +
b10 *
b11001 )
#115
0!
#120
0"
#125
b111 5
1!
#127
b111 0
b1100111001110111100000000000 /
b11011 #
b1000100010000000000000 %
#130
1"
#132
b111100000000000 ,
b111 -
b1100111001110111100000000000 +
bx *
bx )
b11011 1
b1000100010000000000000 2
#135
0!
#140
0"
#145
b1000 5
1!
#147
bx #
b1100111001110111100000000000 %
b1000 0
b100000110010100000000000 /
#150
1"
#152
bx 1
b1100111001110111100000000000 2
b10100000000000 ,
b1000 -
b100000110010100000000000 +
b11 *
b11011 )
#155
0!
#160
0"
#165
b1001 5
1!
#167
b1001 0
bx /
b11110 #
b100000110010100000000000 %
#170
1"
#172
bx ,
b1001 -
bx +
bx *
bx )
b11110 1
b100000110010100000000000 2
#175
0!
#180
0"
#185
b1010 5
1!
#187
bx %
b1010 0
#190
1"
#192
bx 2
b1010 -
#195
0!
#200
0"
#205
b1011 5
1!
#207
b1011 0
#210
1"
#212
b1011 -
#215
0!
#220
0"
#225
b1100 5
1!
#227
b1100 0
#230
1"
#232
b1100 -
#235
0!
#240
0"
#245
b1101 5
1!
#247
b1101 0
b11111100000000000000000000000000 /
#250
b0 *
b0 )
1"
#252
b101 .
b0 ,
b1101 -
b11111100000000000000000000000000 +
#255
0!
#260
0"
#265
b1110 5
1!
#267
b11111100000000000000000000000000 %
b101 '
b1110 0
bx /
#270
1"
#272
b11111100000000000000000000000000 2
b101 4
bx ,
b1110 -
bx +
bx *
bx )
#275
0!
#280
0"
#285
b1111 5
1!
#287
b1111 0
bx %
1(
